{
  "tenantId": "bh",
  "moduleName": "tenant",
  "tenants": [
    {
      "code": "bh.patna",
      "name": "Patna",
      "description": "Patna",
      "logoId": "https://s3.ap-south-1.amazonaws.com/pb-egov-assets/pb.testing/patnalogo.jpg",
      "imageId": null,
      "domainUrl": "https://patnamunicipal.net/pmc/public",
      "type": "CITY",
      "twitterUrl": null,
      "facebookUrl": null,
      "emailId": null,
      "OfficeTimings": {
        "Mon - Sat": "10.00 AM - 5.00 PM"
      },
      "city": {
        "name": "Patna",
        "localName": "Patna",
        "districtCode": "49",
        "districtName": "Patna",
        "regionName": null,
        "ulbGrade": "MC Class I",
        "longitude": 85.1376,
        "latitude": 25.5941,
        "shapeFileLocation": null,
        "captcha": null,
        "code": "248430",
        "regionCode": null,
        "municipalityName": "Patna Municipal Corporation"
      },
      "address": "Not Available",
      "contactNumber": "0135-2653572"
    }
  ]
}